mdquery/__init__.py
mdquery/adaptive_formatting.py
mdquery/advanced_queries.py
mdquery/auto_config.py
mdquery/cache.py
mdquery/cli.py
mdquery/concurrent.py
mdquery/config.py
mdquery/config_generator.py
mdquery/database.py
mdquery/directory_setup.py
mdquery/error_recovery.py
mdquery/exceptions.py
mdquery/indexer.py
mdquery/logging_config.py
mdquery/mcp.py
mdquery/mcp_server.py
mdquery/migration_tools.py
mdquery/models.py
mdquery/performance.py
mdquery/query.py
mdquery/query_guidance.py
mdquery/research.py
mdquery/tag_analysis.py
mdquery/tool_interface.py
mdquery/workflow_analysis.py
mdquery/parsers/__init__.py
mdquery/parsers/frontmatter.py
mdquery/parsers/links.py
mdquery/parsers/markdown.py
mdquery/parsers/obsidian.py
mdquery/parsers/tags.py
mdquery-0.4.0.dist-info/METADATA
mdquery-0.4.0.dist-info/WHEEL
mdquery-0.4.0.dist-info/entry_points.txt
mdquery-0.4.0.dist-info/top_level.txt
mdquery-0.4.0.dist-info/RECORD
