Metadata-Version: 2.1
Name: mdquery
Version: 0.4.0
Summary: Universal markdown querying tool with SQL-like syntax
Home-page: https://github.com/yourusername/mdquery
Author: mdquery
Author-email: 
Keywords: markdown,query,sql,search,obsidian,jekyll,static-site-generator
Classifier: Development Status :: 3 - Alpha
Classifier: Intended Audience :: Developers
Classifier: License :: OSI Approved :: MIT License
Classifier: Programming Language :: Python :: 3
Classifier: Programming Language :: Python :: 3.8
Classifier: Programming Language :: Python :: 3.9
Classifier: Programming Language :: Python :: 3.10
Classifier: Programming Language :: Python :: 3.11
Classifier: Programming Language :: Python :: 3.12
Classifier: Topic :: Software Development :: Libraries :: Python Modules
Classifier: Topic :: Text Processing :: Markup
Classifier: Topic :: Utilities
Requires-Python: >=3.8
Requires-Dist: python-frontmatter>=1.0.0
Requires-Dist: PyYAML>=6.0.0
Requires-Dist: toml>=0.10.0
Requires-Dist: click>=8.0.0
Requires-Dist: markdown>=3.4.0
Requires-Dist: typing-extensions>=4.0.0
Requires-Dist: psutil>=5.8.0
Requires-Dist: mcp>=1.0.0
